py_eloquent/__init__.py
py_eloquent/connection.py
py_eloquent/exceptions.py
py_eloquent/fields.py
py_eloquent/model.py
py_eloquent/query.py
py_eloquent-0.1.0.dist-info/METADATA
py_eloquent-0.1.0.dist-info/WHEEL
py_eloquent-0.1.0.dist-info/top_level.txt
py_eloquent-0.1.0.dist-info/RECORD
