Metadata-Version: 2.4
Name: py-eloquent
Version: 0.1.0
Summary: A tiny Eloquent-like ORM for Python + MySQL (inspired by Laravel Eloquent)
Author: Meysam Afghan
Project-URL: Repository, https://github.com/hshmatullahnoor/pyLaravel-orm
Requires-Python: >=3.8
Requires-Dist: pymysql>=1.0
